anime_sama_api/__init__.py
anime_sama_api/catalogue.py
anime_sama_api/episode.py
anime_sama_api/langs.py
anime_sama_api/season.py
anime_sama_api/top_level.py
anime_sama_api/utils.py
anime_sama_api/cli/__main__.py
anime_sama_api/cli/config.py
anime_sama_api/cli/config.toml
anime_sama_api/cli/downloader.py
anime_sama_api/cli/episode_extra_info.py
anime_sama_api/cli/error_handeling.py
anime_sama_api/cli/internal_player.py
anime_sama_api/cli/play_menu.py
anime_sama_api/cli/utils.py
anime_sama_api-0.2.2.post3.dist-info/METADATA
anime_sama_api-0.2.2.post3.dist-info/WHEEL
anime_sama_api-0.2.2.post3.dist-info/entry_points.txt
anime_sama_api-0.2.2.post3.dist-info/licenses/LICENSE
anime_sama_api-0.2.2.post3.dist-info/RECORD
