Metadata-Version: 2.4
Name: anime-sama_api
Version: 0.2.2.post3
Summary: Api for anime-sama
Project-URL: Repository, https://github.com/Sky-NiniKo/anime-sama_api/
Author-email: NiniKo <pcninik@gmail.com>
License-Expression: GPL-3.0-or-later
License-File: LICENSE
Keywords: anime,anime-sama,downloader
Classifier: Development Status :: 4 - Beta
Classifier: Environment :: Console
Classifier: Intended Audience :: End Users/Desktop
Classifier: License :: OSI Approved :: GNU General Public License v3 or later (GPLv3+)
Classifier: Programming Language :: Python
Classifier: Programming Language :: Python :: 3.10
Classifier: Programming Language :: Python :: 3.11
Classifier: Programming Language :: Python :: 3.12
Classifier: Programming Language :: Python :: 3.13
Classifier: Topic :: Multimedia :: Video :: Capture
Classifier: Topic :: System :: Archiving
Requires-Python: >=3.10
Requires-Dist: httpx>=0.28.1
Provides-Extra: cli
Requires-Dist: platformdirs>=4.5.1; extra == 'cli'
Requires-Dist: rich>=14.2.0; extra == 'cli'
Requires-Dist: tomli>=2.2.1; (python_full_version < '3.11') and extra == 'cli'
Requires-Dist: yt-dlp>=2025.8.22; extra == 'cli'
